{"id": "1", "faixa_de_cep": "63240-000 a 63249-999", "localidade": "Abaiara"}
{"id": "2", "faixa_de_cep": "62785-000 a 62789-999", "localidade": "Acarape"}
{"id": "3", "faixa_de_cep": "62580-000 a 62589-999", "localidade": "Acaraú"}
{"id": "4", "faixa_de_cep": "63560-000 a 63569-999", "localidade": "Acopiara"}
{"id": "5", "faixa_de_cep": "63575-000 a 63579-999", "localidade": "Aiuaba"}
{"id": "6", "faixa_de_cep": "62120-000 a 62129-999", "localidade": "Alcântaras"}
{"id": "7", "faixa_de_cep": "63195-000 a 63199-999", "localidade": "Altaneira"}
{"id": "8", "faixa_de_cep": "62970-000 a 62979-999", "localidade": "Alto Santo"}
{"id": "9", "faixa_de_cep": "62540-000 a 62549-999", "localidade": "Amontada"}
{"id": "10", "faixa_de_cep": "63570-000 a 63574-999", "localidade": "Antonina do Norte"}
{"id": "11", "faixa_de_cep": "62630-000 a 62639-999", "localidade": "Apuiarés"}
{"id": "12", "faixa_de_cep": "61700-000 a 61759-999", "localidade": "Aquiraz"}
{"id": "13", "faixa_de_cep": "62800-000 a 62809-999", "localidade": "Aracati"}
{"id": "14", "faixa_de_cep": "62750-000 a 62754-999", "localidade": "Aracoiaba"}
{"id": "15", "faixa_de_cep": "62210-000 a 62214-999", "localidade": "Ararendá"}
{"id": "16", "faixa_de_cep": "63170-000 a 63179-999", "localidade": "Araripe"}
{"id": "17", "faixa_de_cep": "62762-000 a 62763-999", "localidade": "Aratuba"}
{"id": "18", "faixa_de_cep": "63670-000 a 63679-999", "localidade": "Arneiroz"}
{"id": "19", "faixa_de_cep": "63140-000 a 63144-999", "localidade": "Assaré"}
{"id": "20", "faixa_de_cep": "63360-000 a 63379-999", "localidade": "Aurora"}
{"id": "21", "faixa_de_cep": "63320-000 a 63339-999", "localidade": "Baixio"}
{"id": "22", "faixa_de_cep": "63960-000 a 63969-999", "localidade": "Banabuiú"}
{"id": "23", "faixa_de_cep": "63180-000 a 63184-999", "localidade": "Barbalha"}
{"id": "24", "faixa_de_cep": "62795-000 a 62799-999", "localidade": "Barreira"}
{"id": "25", "faixa_de_cep": "63380-000 a 63399-999", "localidade": "Barro"}
{"id": "26", "faixa_de_cep": "62410-000 a 62419-999", "localidade": "Barroquinha"}
{"id": "27", "faixa_de_cep": "62760-000 a 62761-999", "localidade": "Baturité"}
{"id": "28", "faixa_de_cep": "62840-000 a 62849-999", "localidade": "Beberibe"}
{"id": "29", "faixa_de_cep": "62570-000 a 62579-999", "localidade": "Bela Cruz"}
{"id": "30", "faixa_de_cep": "63870-000 a 63899-999", "localidade": "Boa Viagem"}
{"id": "31", "faixa_de_cep": "63260-000 a 63269-999", "localidade": "Brejo Santo"}
{"id": "32", "faixa_de_cep": "62400-000 a 62409-999", "localidade": "Camocim"}
{"id": "33", "faixa_de_cep": "63150-000 a 63154-999", "localidade": "Campos Sales"}
{"id": "34", "faixa_de_cep": "62700-000 a 62719-999", "localidade": "Canindé"}
{"id": "35", "faixa_de_cep": "62748-000 a 62749-999", "localidade": "Capistrano"}
{"id": "36", "faixa_de_cep": "62730-000 a 62735-999", "localidade": "Caridade"}
{"id": "37", "faixa_de_cep": "62184-000 a 62189-999", "localidade": "Cariré"}
{"id": "38", "faixa_de_cep": "63220-000 a 63229-999", "localidade": "Caririaçu"}
{"id": "39", "faixa_de_cep": "63530-000 a 63539-999", "localidade": "Cariús"}
{"id": "40", "faixa_de_cep": "62375-000 a 62379-999", "localidade": "Carnaubal"}
{"id": "41", "faixa_de_cep": "62850-000 a 62859-999", "localidade": "Cascavel"}
{"id": "42", "faixa_de_cep": "63595-000 a 63599-999", "localidade": "Catarina"}
{"id": "43", "faixa_de_cep": "62297-000 a 62299-999", "localidade": "Catunda"}
{"id": "44", "faixa_de_cep": "61600-001 a 61699-999", "localidade": "Caucaia"}
{"id": "45", "faixa_de_cep": "61600-001 a 61676-999", "localidade": "Codificado por logradouros"}
{"id": "46", "faixa_de_cep": "63400-000 a 63429-999", "localidade": "Caucaia"}
{"id": "47", "faixa_de_cep": "62420-000 a 62429-999", "localidade": "Codificada por logradouros"}
{"id": "48", "faixa_de_cep": "63950-000 a 63959-999", "localidade": "Cedro"}
{"id": "49", "faixa_de_cep": "62875-000 a 62879-999", "localidade": "Chaval"}
